<?xml version="1.0" encoding="utf-8" ?><dwsync><file name="blue.css" server="therprod.brewingtonmedia.com//home/therprod/public_html/" local="3442580906" remote="319783739088257183" Dst="-1" /><file name="coffee.css" server="therprod.brewingtonmedia.com//home/therprod/public_html/" local="3442580906" remote="319783739088257183" Dst="-1" /><file name="default.css" server="therprod.brewingtonmedia.com//home/therprod/public_html/" local="3442580906" remote="319783739088257183" Dst="-1" /><file name="light-blue.css" server="therprod.brewingtonmedia.com//home/therprod/public_html/" local="3442580906" remote="319783739088257184" Dst="-1" /><file name="pomegranate.css" server="therprod.brewingtonmedia.com//home/therprod/public_html/" local="3442580906" remote="319783739088257184" Dst="-1" /><file name="space-orange.css" server="therprod.brewingtonmedia.com//home/therprod/public_html/" local="3442580906" remote="319783739088257185" Dst="-1" /><file name="space-teal.css" server="therprod.brewingtonmedia.com//home/therprod/public_html/" local="3442580906" remote="319783739088257185" Dst="-1" /><file name="space.css" server="therprod.brewingtonmedia.com//home/therprod/public_html/" local="3442580906" remote="319783739088257185" Dst="-1" /><file name="spring.css" server="therprod.brewingtonmedia.com//home/therprod/public_html/" local="3442580906" remote="319783739088257185" Dst="-1" /><file name="white.css" server="therprod.brewingtonmedia.com//home/therprod/public_html/" local="3442580906" remote="319783739088257185" Dst="-1" /><file name="blue.css" server="173.236.50.26//home/therprod/public_html/" local="3442580906" remote="319783739089738112" Dst="-1" /><file name="coffee.css" server="173.236.50.26//home/therprod/public_html/" local="3442580906" remote="319783739089738112" Dst="-1" /><file name="default.css" server="173.236.50.26//home/therprod/public_html/" local="3442580906" remote="319783739089738112" Dst="-1" /><file name="light-blue.css" server="173.236.50.26//home/therprod/public_html/" local="3442580906" remote="319783739089738112" Dst="-1" /><file name="pomegranate.css" server="173.236.50.26//home/therprod/public_html/" local="3442580906" remote="319783739089738112" Dst="-1" /><file name="space-orange.css" server="173.236.50.26//home/therprod/public_html/" local="3442580906" remote="319783739089738112" Dst="-1" /><file name="space-teal.css" server="173.236.50.26//home/therprod/public_html/" local="3442580906" remote="319783739089738112" Dst="-1" /><file name="space.css" server="173.236.50.26//home/therprod/public_html/" local="3442580906" remote="319783739089738113" Dst="-1" /><file name="spring.css" server="173.236.50.26//home/therprod/public_html/" local="3442580906" remote="319783739089738113" Dst="-1" /><file name="white.css" server="173.236.50.26//home/therprod/public_html/" local="3442580906" remote="319783739089738113" Dst="-1" /><file name="blue.css" server="o4961074556.v252n.us.host8.biz" local="3442580906" remote="319783739092686875" Dst="-1" /><file name="coffee.css" server="o4961074556.v252n.us.host8.biz" local="3442580906" remote="319783739092686875" Dst="-1" /><file name="default.css" server="o4961074556.v252n.us.host8.biz" local="3442580906" remote="319783739092686876" Dst="-1" /><file name="light-blue.css" server="o4961074556.v252n.us.host8.biz" local="3442580906" remote="319783739092686876" Dst="-1" /><file name="pomegranate.css" server="o4961074556.v252n.us.host8.biz" local="3442580906" remote="319783739092686876" Dst="-1" /><file name="space-orange.css" server="o4961074556.v252n.us.host8.biz" local="3442580906" remote="319783739092686876" Dst="-1" /><file name="space-teal.css" server="o4961074556.v252n.us.host8.biz" local="3442580906" remote="319783739092686876" Dst="-1" /><file name="space.css" server="o4961074556.v252n.us.host8.biz" local="3442580906" remote="319783739092686876" Dst="-1" /><file name="spring.css" server="o4961074556.v252n.us.host8.biz" local="3442580906" remote="319783739092686876" Dst="-1" /><file name="white.css" server="o4961074556.v252n.us.host8.biz" local="3442580906" remote="319783739092686876" Dst="-1" /></dwsync>